{"cameraMode":{"drawMode":0,"name":"Shaded","section":"Shading Mode"},"sceneLighting":false,"audioPlay":false,"sceneViewState":{"m_AlwaysRefresh":false,"showFog":true,"showSkybox":false,"showFlares":true,"showImageEffects":true,"showParticleSystems":true,"showVisualEffectGraphs":true,"m_FxEnabled":true},"in2DMode":false,"pivot":{"x":0.040507782250642779,"y":0.04749308153986931,"z":-0.0052611553110182289},"rotation":{"x":0.0,"y":0.7071068286895752,"z":0.0,"w":0.7071068286895752},"size":1.0852917432785035,"orthographic":false}